setup.py
WorkingWithDocumentConversion/__init__.py
WorkingWithDocumentObject/__init__.py
WorkingWithPages/__init__.py
WorkingWithText/__init__.py
aspose_pdf_java_for_python.egg-info/PKG-INFO
aspose_pdf_java_for_python.egg-info/SOURCES.txt
aspose_pdf_java_for_python.egg-info/dependency_links.txt
aspose_pdf_java_for_python.egg-info/top_level.txt