Metadata-Version: 1.1
Name: aspose-pdf-java-for-python
Version: 1.0.0
Summary: Aspose.Pdf Java for Python
Home-page: https://github.com/asposepdf/Aspose_Pdf_Java/tree/master/Plugins/Aspose_Pdf_Java_for_Python
Author: Fahad Adeel
Author-email: fahadadeel@gmail.com
License: UNKNOWN
Platform: UNKNOWN
Classifier: Programming Language :: Python
Classifier: Programming Language :: Python :: 2
Classifier: License :: OSI Approved :: MIT License
Classifier: Operating System :: OS Independent
